decthings_api/__init__.py
decthings_api/client.py
decthings_api/client_sync.py
decthings_api/event.py
decthings_api/protocol.py
decthings_api/tensor.py
decthings_api/varint.py
decthings_api/ws.py
decthings_api/rpc_impl/convert.py
decthings_api/rpc_impl/dataset.py
decthings_api/rpc_impl/debug.py
decthings_api/rpc_impl/fs.py
decthings_api/rpc_impl/language.py
decthings_api/rpc_impl/model.py
decthings_api/rpc_impl/persistent_launcher.py
decthings_api/rpc_impl/spawned.py
decthings_api/rpc_impl/team.py
decthings_api/rpc_impl/terminal.py
decthings_api/rpc_impl/user.py
decthings_api-0.0.4.dist-info/LICENSE
decthings_api-0.0.4.dist-info/METADATA
decthings_api-0.0.4.dist-info/WHEEL
decthings_api-0.0.4.dist-info/top_level.txt
decthings_api-0.0.4.dist-info/RECORD
