Metadata-Version: 2.1
Name: decthings-api
Version: 0.0.4
Summary: Official Python API client for Decthings
Project-URL: Homepage, https://github.com/decthings/api-client-py
Classifier: Programming Language :: Python :: 3
Classifier: License :: OSI Approved :: MIT License
Classifier: Operating System :: OS Independent
Requires-Python: >=3.6
License-File: LICENSE
Requires-Dist: aiohttp >=3
Requires-Dist: numpy >=1
Requires-Dist: requests >=2
Requires-Dist: websockets >=13
